image_uploader/__init__.py
image_uploader/frontend/dist/index.html
image_uploader/frontend/dist/vite.svg
image_uploader/frontend/dist/assets/index-BuLsgOtb.css
image_uploader/frontend/dist/assets/index-CYr_P5v9.js
image_uploder/__init__.py
streamlit_image_uploader-0.0.2.dist-info/METADATA
streamlit_image_uploader-0.0.2.dist-info/WHEEL
streamlit_image_uploader-0.0.2.dist-info/top_level.txt
streamlit_image_uploader-0.0.2.dist-info/RECORD
